{
	"configurations" : 
	[
		{
			"directories" : 
			[
				{
					"build" : ".",
					"jsonFile" : "directory-.-Debug-f5ebdc15457944623624.json",
					"minimumCMakeVersion" : 
					{
						"string" : "3.10"
					},
					"projectIndex" : 0,
					"source" : ".",
					"targetIndexes" : 
					[
						0
					]
				}
			],
			"name" : "Debug",
			"projects" : 
			[
				{
					"directoryIndexes" : 
					[
						0
					],
					"name" : "ft_ls",
					"targetIndexes" : 
					[
						0
					]
				}
			],
			"targets" : 
			[
				{
					"directoryIndex" : 0,
					"id" : "ft_ls::@6890427a1f51a3e7e1df",
					"jsonFile" : "target-ft_ls-Debug-48aac4c6b82332717b59.json",
					"name" : "ft_ls",
					"projectIndex" : 0
				}
			]
		}
	],
	"kind" : "codemodel",
	"paths" : 
	{
		"build" : "/mnt/c/Users/M4x/Desktop/42/ft_ls/cmake-build-debug",
		"source" : "/mnt/c/Users/M4x/Desktop/42/ft_ls"
	},
	"version" : 
	{
		"major" : 2,
		"minor" : 4
	}
}
